obsidian_sync/__init__.py
obsidian_sync/cli.py
obsidian_sync/config.py
obsidian_sync/git_handler.py
obsidian_sync/sync.py
obsidian_sync/transformer.py
ob_sync-0.1.2.dist-info/METADATA
ob_sync-0.1.2.dist-info/WHEEL
ob_sync-0.1.2.dist-info/entry_points.txt
ob_sync-0.1.2.dist-info/top_level.txt
ob_sync-0.1.2.dist-info/RECORD
