Metadata-Version: 2.4
Name: ob-sync
Version: 0.1.2
Summary: Sync Obsidian vault to GitHub with wiki-link transformation
Author-email: Sounak Gupta <sounakume@gmail.com>
License: MIT
Project-URL: Homepage, https://github.com/sounak07/obsidian-transformer
Project-URL: Repository, https://github.com/sounak07/obsidian-transformer
Project-URL: Issues, https://github.com/sounak07/obsidian-transformer/issues
Keywords: obsidian,github,sync,markdown,wiki-links
Classifier: Development Status :: 4 - Beta
Classifier: Environment :: Console
Classifier: Intended Audience :: Developers
Classifier: License :: OSI Approved :: MIT License
Classifier: Operating System :: OS Independent
Classifier: Programming Language :: Python :: 3
Classifier: Programming Language :: Python :: 3.9
Classifier: Programming Language :: Python :: 3.10
Classifier: Programming Language :: Python :: 3.11
Classifier: Programming Language :: Python :: 3.12
Classifier: Topic :: Utilities
Requires-Python: >=3.9
Requires-Dist: click>=8.0
Requires-Dist: gitpython>=3.1
Requires-Dist: pyyaml>=6.0
Requires-Dist: pathspec>=0.11
